limr/.DS_Store
limr/.ipynb_checkpoints/loader-checkpoint.py
limr/.ipynb_checkpoints/utils-checkpoint.py
limr/__init__.py
limr/data/.DS_Store
limr/data/prod_model/.DS_Store
limr/data/prod_model/20251109_remnant_model/final_mass_tinygp_model.pkl
limr/data/prod_model/20251109_remnant_model/final_spin_tinygp_model.pkl
limr/data/prod_model/20251215_using_calibration_set_pofh_gp_model/gp_amplitudes__2_1.pkl
limr/data/prod_model/20251215_using_calibration_set_pofh_gp_model/gp_amplitudes__2_2.pkl
limr/data/prod_model/20251215_using_calibration_set_pofh_gp_model/gp_amplitudes__3_3.pkl
limr/data/prod_model/20251215_using_calibration_set_pofh_gp_model/gp_amplitudes__4_4.pkl
limr/data/prod_model/20251215_using_calibration_set_pofh_gp_model/gp_amplitudes__5_5.pkl
limr/data/prod_model/20251215_using_calibration_set_pofh_gp_model/gp_hlms_real__3_2.pkl
limr/data/prod_model/20251215_using_calibration_set_pofh_gp_model/gp_hlms_real__4_3.pkl
limr/data/prod_model/20251215_using_calibration_set_pofh_gp_model/gp_hlms_real__5_4.pkl
limr/data/prod_model/20251215_using_calibration_set_pofh_gp_model/gp_phases__2_1.pkl
limr/data/prod_model/20251215_using_calibration_set_pofh_gp_model/gp_phases__2_2.pkl
limr/data/prod_model/20251215_using_calibration_set_pofh_gp_model/gp_phases__3_3.pkl
limr/data/prod_model/20251215_using_calibration_set_pofh_gp_model/gp_phases__4_4.pkl
limr/data/prod_model/20251215_using_calibration_set_pofh_gp_model/gp_phases__5_5.pkl
limr/data/prod_model/20251216_using_calibration_set_pofh_gp_model_inspiral_model/gp_amplitudes__2_1.pkl
limr/data/prod_model/20251216_using_calibration_set_pofh_gp_model_inspiral_model/gp_amplitudes__2_2.pkl
limr/data/prod_model/20251216_using_calibration_set_pofh_gp_model_inspiral_model/gp_amplitudes__3_2.pkl
limr/data/prod_model/20251216_using_calibration_set_pofh_gp_model_inspiral_model/gp_amplitudes__3_3.pkl
limr/data/prod_model/20251216_using_calibration_set_pofh_gp_model_inspiral_model/gp_amplitudes__4_3.pkl
gw_limr-0.2.4.dist-info/licenses/LICENSE
gw_limr-0.2.4.dist-info/WHEEL
gw_limr-0.2.4.dist-info/METADATA
gw_limr-0.2.4.dist-info/RECORD
